pywebcrwl/__init__.py
pywebcrwl/core.py
pywebcrwl-0.1.2.dist-info/LICENSE.txt
pywebcrwl-0.1.2.dist-info/METADATA
pywebcrwl-0.1.2.dist-info/WHEEL
pywebcrwl-0.1.2.dist-info/top_level.txt
pywebcrwl-0.1.2.dist-info/RECORD
