Metadata-Version: 2.1
Name: pywebcrwl
Version: 0.1.2
Summary: Web crawling tool
Author-email: idriss1433@gmail.com
Project-URL: Homepage and Documentation, https://github.com/NoneToRoot/pywebcrwl
Classifier: Programming Language :: Python :: 3
Classifier: License :: OSI Approved :: MIT License
Classifier: Operating System :: OS Independent
Requires-Python: >=3.7
License-File: LICENSE.txt
Requires-Dist: requests
Requires-Dist: beautifulsoup4
Requires-Dist: phonenumbers
Requires-Dist: geotext
